README.md
setup.py
kubecd/__init__.py
kubecd/github.py
kubecd/helm.py
kubecd/inspection.py
kubecd/model.py
kubecd/providers.py
kubecd/semver.py
kubecd/thriftutils.py
kubecd/updates.py
kubecd/utils.py
kubecd.egg-info/PKG-INFO
kubecd.egg-info/SOURCES.txt
kubecd.egg-info/dependency_links.txt
kubecd.egg-info/entry_points.txt
kubecd.egg-info/requires.txt
kubecd.egg-info/top_level.txt
kubecd/cli/__init__.py
kubecd/cli/commands.py
kubecd/cli/e2e_test.py
kubecd/cli/e2e/__init__.py
kubecd/gen_py/__init__.py
kubecd/gen_py/constants.py
kubecd/gen_py/ttypes.py
kubecd/tests/__init__.py
kubecd/tests/helm_test.py
kubecd/tests/providers_test.py
kubecd/tests/semver_test.py
kubecd/tests/updates_test.py