Metadata-Version: 1.2
Name: kubecd
Version: 0.42.1
Summary: Kubernetes Continuous Deployment and Inventory Tool
Home-page: http://github.com/zedge/kubecd
Author: Stig Bakken
Author-email: stig@zedge.net
License: Apache 2
Platform: UNKNOWN
Requires-Python: >=3.5.0
